MainHelper7-0.0.1.data/data/main_helper7/AB.bin
main_helper7/AB.bin
main_helper7/__init__.py
main_helper7/adressbook.py
main_helper7/cleanfolder.py
main_helper7/file_parser.py
main_helper7/main.py
main_helper7/normalize.py
venv/Lib/site-packages/_virtualenv.py
venv/Lib/site-packages/_distutils_hack/__init__.py
venv/Lib/site-packages/_distutils_hack/override.py
venv/Lib/site-packages/build/__init__.py
venv/Lib/site-packages/build/__main__.py
venv/Lib/site-packages/build/env.py
venv/Lib/site-packages/build/util.py
venv/Lib/site-packages/colorama/__init__.py
venv/Lib/site-packages/colorama/ansi.py
venv/Lib/site-packages/colorama/ansitowin32.py
venv/Lib/site-packages/colorama/initialise.py
venv/Lib/site-packages/colorama/win32.py
venv/Lib/site-packages/colorama/winterm.py
venv/Lib/site-packages/packaging/__about__.py
venv/Lib/site-packages/packaging/__init__.py
venv/Lib/site-packages/packaging/_manylinux.py
venv/Lib/site-packages/packaging/_musllinux.py
venv/Lib/site-packages/packaging/_structures.py
venv/Lib/site-packages/packaging/markers.py
venv/Lib/site-packages/packaging/requirements.py
venv/Lib/site-packages/packaging/specifiers.py
venv/Lib/site-packages/packaging/tags.py
venv/Lib/site-packages/packaging/utils.py
venv/Lib/site-packages/packaging/version.py
venv/Lib/site-packages/pep517/__init__.py
venv/Lib/site-packages/pep517/build.py
venv/Lib/site-packages/pep517/check.py
venv/Lib/site-packages/pep517/colorlog.py
venv/Lib/site-packages/pep517/compat.py
venv/Lib/site-packages/pep517/dirtools.py
venv/Lib/site-packages/pep517/envbuild.py
venv/Lib/site-packages/pep517/meta.py
venv/Lib/site-packages/pep517/wrappers.py
venv/Lib/site-packages/pep517/in_process/__init__.py
venv/Lib/site-packages/pep517/in_process/_in_process.py
venv/Lib/site-packages/pip/__init__.py
venv/Lib/site-packages/pip/__main__.py
venv/Lib/site-packages/pip/_internal/__init__.py
venv/Lib/site-packages/pip/_internal/build_env.py
venv/Lib/site-packages/pip/_internal/cache.py
MainHelper7-0.0.1.dist-info/LICENSE
MainHelper7-0.0.1.dist-info/METADATA
MainHelper7-0.0.1.dist-info/WHEEL
MainHelper7-0.0.1.dist-info/entry_points.txt
MainHelper7-0.0.1.dist-info/top_level.txt
MainHelper7-0.0.1.dist-info/RECORD
